hyv_touch/__init__.py
hyv_touch/__main__.py
hyv_touch/demo.py
hyv_touch/edit.py
hyv_touch/embrace.py
hyv_touch/feel.py
hyv_touch/retouch.py
hyv_touch/shared.py
hyv_touch/source.py
hyv_touch/tickle.py
hyv_touch/touch.py
hyv_touch-0.1.2.dist-info/METADATA
hyv_touch-0.1.2.dist-info/WHEEL
hyv_touch-0.1.2.dist-info/entry_points.txt
hyv_touch-0.1.2.dist-info/licenses/LICENSE
hyv_touch-0.1.2.dist-info/RECORD
