Metadata-Version: 2.4
Name: hyv-touch
Version: 0.1.2
Summary: Rich-powered interactive touch REPL for introspection and debugging
Project-URL: Homepage, https://github.com/hyvnova/touch
Project-URL: Repository, https://github.com/hyvnova/touch
Project-URL: Issues, https://github.com/hyvnova/touch/issues
Author: Hyv
License: MIT
License-File: LICENSE
Keywords: cli,debugger,introspection,repl,rich
Classifier: Development Status :: 3 - Alpha
Classifier: Intended Audience :: Developers
Classifier: License :: OSI Approved :: MIT License
Classifier: Programming Language :: Python :: 3
Classifier: Programming Language :: Python :: 3 :: Only
Classifier: Programming Language :: Python :: 3.9
Classifier: Programming Language :: Python :: 3.10
Classifier: Programming Language :: Python :: 3.11
Classifier: Programming Language :: Python :: 3.12
Classifier: Topic :: Software Development :: Debuggers
Classifier: Topic :: Terminals
Requires-Python: >=3.9
Requires-Dist: rich>=13.7
Requires-Dist: typing-extensions>=4.8; python_version < '3.11'
Provides-Extra: dev
Requires-Dist: black>=24.3; extra == 'dev'
Requires-Dist: build>=1.2.1; extra == 'dev'
Requires-Dist: mypy>=1.9; extra == 'dev'
Requires-Dist: ruff>=0.5; extra == 'dev'
Requires-Dist: twine>=5.0; extra == 'dev'
